PyTechBrain/PyTechBrain.py
PyTechBrain/__init__.py
PyTechBrain-0.8.4.dist-info/METADATA
PyTechBrain-0.8.4.dist-info/WHEEL
PyTechBrain-0.8.4.dist-info/top_level.txt
PyTechBrain-0.8.4.dist-info/RECORD
