Metadata-Version: 2.1
Name: PyTechBrain
Version: 0.8.4
Summary: PyTechBrain to nowa platforma wprowadzająca uczniów w dziedzinę IoT - Internet of Things (Internet Rzeczy). Działa z Python 3.6
Home-page: https://pytechbrain.edu.pl
Author: Adam Jurkiewicz
Author-email: pytechbrain@abixedukacja.eu
License: UNKNOWN
Keywords: Arduino PyFirmata Laboratoriaprzyszłości
Platform: UNKNOWN
Classifier: Programming Language :: Python :: 3
Classifier: License :: OSI Approved :: GNU General Public License v3 (GPLv3)
Classifier: Operating System :: OS Independent
Classifier: Intended Audience :: Education
Requires-Python: >=3.6
Requires-Dist: pymata-aio
Requires-Dist: snakemd
